{"name":"HODL_AvAtArs #394","id":394,"img":"394.png","rarityScore":83.24826,"rarityRank":120,"attributes":[{"type":"Guardian","value":"ETH","rarity":0.01980198,"rarityScore":50.5,"ignoredForRarity":false,"ignoredForDisplay":false},{"type":"Aura","value":"Turquoise","rarity":0.10351035,"rarityScore":9.66087,"ignoredForRarity":false,"ignoredForDisplay":false},{"type":"World","value":"Skyworld Robot","rarity":0.19171917,"rarityScore":5.2159624,"ignoredForRarity":false,"ignoredForDisplay":false},{"type":"Role","value":"Audit Guardian","rarity":0.12601261,"rarityScore":7.9357142,"ignoredForRarity":false,"ignoredForDisplay":false},{"type":"Tribe","value":"Warrior","rarity":0.12601261,"rarityScore":7.9357142,"ignoredForRarity":false,"ignoredForDisplay":false},{"type":"Energy","value":"Hash Power","rarity":1,"rarityScore":1,"ignoredForRarity":false,"ignoredForDisplay":false},{"type":"Royalty Code","value":"QR Code","rarity":1,"rarityScore":1,"ignoredForRarity":false,"ignoredForDisplay":false}],"prices":{"KRV":223.08545,"KARV_NOW":1043.8168,"KARV_FUTURE":6377.7207,"KHRV":103.9999,"KHRV_NOW":486.61554,"KHRV_FUTURE":2973.221},"comingSoon":false}