{"name":"Stargaze Troopers #1062","id":1062,"img":"1062.png","rarityScore":187.00212,"rarityRank":683,"attributes":[{"type":"Background","value":"Outerworld","rarity":0.035063975,"rarityScore":28.519299,"ignoredForRarity":false,"ignoredForDisplay":false},{"type":"Attribute","value":"Sadist","rarity":0.015871063,"rarityScore":63.00775,"ignoredForRarity":false,"ignoredForDisplay":false},{"type":"Armor","value":"Imperial","rarity":0.060285434,"rarityScore":16.587755,"ignoredForRarity":false,"ignoredForDisplay":false},{"type":"Insigna","value":"Angel Wings","rarity":0.021284448,"rarityScore":46.98266,"ignoredForRarity":false,"ignoredForDisplay":false},{"type":"Helmet","value":"Space General","rarity":0.04515256,"rarityScore":22.147139,"ignoredForRarity":false,"ignoredForDisplay":false},{"type":"Weapon","value":"None","rarity":0.10248524,"rarityScore":9.757503,"ignoredForRarity":false,"ignoredForDisplay":false}],"prices":{"KRV":371.2421,"KARV_NOW":1737.0417,"KARV_FUTURE":10613.325,"KHRV":130.92126,"KHRV_NOW":612.58057,"KHRV_FUTURE":3742.8674}}