{"name":"Stargaze Troopers #3290","id":3290,"img":"3290.png","rarityScore":97.63945,"rarityRank":5512,"attributes":[{"type":"Background","value":"Morning Light","rarity":0.09018209,"rarityScore":11.088676,"ignoredForRarity":false,"ignoredForDisplay":false},{"type":"Attribute","value":"Agile","rarity":0.050565943,"rarityScore":19.776155,"ignoredForRarity":false,"ignoredForDisplay":false},{"type":"Armor","value":"Battlesuit","rarity":0.036294293,"rarityScore":27.552542,"ignoredForRarity":false,"ignoredForDisplay":false},{"type":"Insigna","value":"STARS","rarity":0.07972441,"rarityScore":12.54321,"ignoredForRarity":false,"ignoredForDisplay":false},{"type":"Helmet","value":"Red, Blue Visor","rarity":0.070743114,"rarityScore":14.135653,"ignoredForRarity":false,"ignoredForDisplay":false},{"type":"Weapon","value":"Medpack","rarity":0.07972441,"rarityScore":12.54321,"ignoredForRarity":false,"ignoredForDisplay":false}],"prices":{"KRV":193.8367,"KARV_NOW":906.9619,"KARV_FUTURE":5541.5376,"KHRV":129.51424,"KHRV_NOW":605.9971,"KHRV_FUTURE":3702.642}}