{"name":"Stargaze Troopers #4669","id":4669,"img":"4669.png","rarityScore":164.12683,"rarityRank":1129,"attributes":[{"type":"Background","value":"Interstellar","rarity":0.08759843,"rarityScore":11.41573,"ignoredForRarity":false,"ignoredForDisplay":false},{"type":"Attribute","value":"Leadership","rarity":0.1027313,"rarityScore":9.734132,"ignoredForRarity":false,"ignoredForDisplay":false},{"type":"Armor","value":"Blood Red","rarity":0.092519686,"rarityScore":10.808511,"ignoredForRarity":false,"ignoredForDisplay":false},{"type":"Insigna","value":"Special Forces","rarity":0.019315945,"rarityScore":51.770702,"ignoredForRarity":false,"ignoredForDisplay":false},{"type":"Helmet","value":"Raynor","rarity":0.014640748,"rarityScore":68.30252,"ignoredForRarity":false,"ignoredForDisplay":false},{"type":"Weapon","value":"War Axe","rarity":0.08267716,"rarityScore":12.095238,"ignoredForRarity":false,"ignoredForDisplay":false}],"prices":{"KRV":325.8294,"KARV_NOW":1524.5558,"KARV_FUTURE":9315.036,"KHRV":130.5611,"KHRV_NOW":610.8954,"KHRV_FUTURE":3732.5708},"comingSoon":false}