{"name":"Stargaze Troopers #6494","id":6494,"img":"6494.png","rarityScore":80.28332,"rarityRank":7551,"attributes":[{"type":"Background","value":"Atmosphere","rarity":0.08661418,"rarityScore":11.545455,"ignoredForRarity":false,"ignoredForDisplay":false},{"type":"Attribute","value":"Charisma","rarity":0.110605314,"rarityScore":9.041157,"ignoredForRarity":false,"ignoredForDisplay":false},{"type":"Armor","value":"Imperial Officer","rarity":0.058809057,"rarityScore":17.004185,"ignoredForRarity":false,"ignoredForDisplay":false},{"type":"Insigna","value":"Rebel","rarity":0.08526082,"rarityScore":11.728716,"ignoredForRarity":false,"ignoredForDisplay":false},{"type":"Helmet","value":"Red, Blue Visor","rarity":0.070743114,"rarityScore":14.135653,"ignoredForRarity":false,"ignoredForDisplay":false},{"type":"Weapon","value":"Gatling Gun","rarity":0.059424214,"rarityScore":16.828157,"ignoredForRarity":false,"ignoredForDisplay":false}],"prices":{"KRV":159.3808,"KARV_NOW":745.74274,"KARV_FUTURE":4556.4883,"KHRV":129.24095,"KHRV_NOW":604.7184,"KHRV_FUTURE":3694.8293}}