{"name":"Acre NFT","id":2243,"img":"2243.png","rarityScore":53.07052,"rarityRank":2331,"attributes":[{"type":"background","value":"Cloudy Weather","rarity":0.1196281,"rarityScore":8.359241,"ignoredForRarity":false,"ignoredForDisplay":false},{"type":"base","value":"Temperate Deciduous Forest","rarity":0.49524793,"rarityScore":2.0191905,"ignoredForRarity":false,"ignoredForDisplay":false},{"type":"life above","value":"Monarch Butterfly","rarity":0.08987603,"rarityScore":11.126437,"ignoredForRarity":false,"ignoredForDisplay":false},{"type":"life below","value":"Worms","rarity":0.104752064,"rarityScore":9.546351,"ignoredForRarity":false,"ignoredForDisplay":false},{"type":"tree","value":"Cottonwood","rarity":0.116115704,"rarityScore":8.6121,"ignoredForRarity":false,"ignoredForDisplay":false},{"type":"microorganism","value":"Predator Nematode","rarity":0.07458678,"rarityScore":13.407202,"ignoredForRarity":false,"ignoredForDisplay":false}],"prices":{"KRV":165.75096,"KARV_NOW":775.5487,"KARV_FUTURE":4738.6025,"KHRV":156.09961,"KHRV_NOW":730.3901,"KHRV_FUTURE":4462.6836}}