{"name":"Acre NFT","id":2640,"img":"2640.png","rarityScore":52.634876,"rarityRank":3314,"attributes":[{"type":"background","value":"Forest Fire","rarity":0.12809917,"rarityScore":7.806452,"ignoredForRarity":false,"ignoredForDisplay":false},{"type":"base","value":"Grassland Soil Base","rarity":0.50475204,"rarityScore":1.9811707,"ignoredForRarity":false,"ignoredForDisplay":false},{"type":"life above","value":"Mosquito","rarity":0.089049585,"rarityScore":11.229698,"ignoredForRarity":false,"ignoredForDisplay":false},{"type":"life below","value":"Texas Toad","rarity":0.1018595,"rarityScore":9.817444,"ignoredForRarity":false,"ignoredForDisplay":false},{"type":"tree","value":"Red Maple","rarity":0.116115704,"rarityScore":8.6121,"ignoredForRarity":false,"ignoredForDisplay":false},{"type":"microorganism","value":"Actinomycetes","rarity":0.075826444,"rarityScore":13.188011,"ignoredForRarity":false,"ignoredForDisplay":false}],"prices":{"KRV":164.39037,"KARV_NOW":769.1825,"KARV_FUTURE":4699.705,"KHRV":156.08571,"KHRV_NOW":730.325,"KHRV_FUTURE":4462.286},"comingSoon":false,"hidden":false}