{"name":"Acre NFT","id":2988,"img":"2988.png","rarityScore":52.2101,"rarityRank":4000,"attributes":[{"type":"background","value":"Clear Skies Sunny Weather","rarity":0.13450414,"rarityScore":7.4347157,"ignoredForRarity":false,"ignoredForDisplay":false},{"type":"base","value":"Grassland Soil Base","rarity":0.50475204,"rarityScore":1.9811707,"ignoredForRarity":false,"ignoredForDisplay":false},{"type":"life above","value":"Bumblebee","rarity":0.09028926,"rarityScore":11.075515,"ignoredForRarity":false,"ignoredForDisplay":false},{"type":"life below","value":"Black Footed Ferrets","rarity":0.103099175,"rarityScore":9.699399,"ignoredForRarity":false,"ignoredForDisplay":false},{"type":"tree","value":"Red Maple","rarity":0.116115704,"rarityScore":8.6121,"ignoredForRarity":false,"ignoredForDisplay":false},{"type":"microorganism","value":"Predator Nematode","rarity":0.07458678,"rarityScore":13.407202,"ignoredForRarity":false,"ignoredForDisplay":false}],"prices":{"KRV":163.06367,"KARV_NOW":762.9749,"KARV_FUTURE":4661.777,"KHRV":156.07216,"KHRV_NOW":730.2616,"KHRV_FUTURE":4461.8984},"comingSoon":false}