{"name":"Acre NFT","id":4426,"img":"4426.png","rarityScore":53.840324,"rarityRank":742,"attributes":[{"type":"background","value":"Cloudy Weather","rarity":0.1196281,"rarityScore":8.359241,"ignoredForRarity":false,"ignoredForDisplay":false},{"type":"base","value":"Grassland Soil Base","rarity":0.50475204,"rarityScore":1.9811707,"ignoredForRarity":false,"ignoredForDisplay":false},{"type":"life above","value":"Cloudless Sulphur","rarity":0.09152892,"rarityScore":10.925508,"ignoredForRarity":false,"ignoredForDisplay":false},{"type":"life below","value":"Underground Mouse","rarity":0.10123967,"rarityScore":9.877551,"ignoredForRarity":false,"ignoredForDisplay":false},{"type":"tree","value":"Honey locust_","rarity":0.10516529,"rarityScore":9.508841,"ignoredForRarity":false,"ignoredForDisplay":false},{"type":"microorganism","value":"Actinomycetes","rarity":0.075826444,"rarityScore":13.188011,"ignoredForRarity":false,"ignoredForDisplay":false}],"prices":{"KRV":168.15523,"KARV_NOW":786.7983,"KARV_FUTURE":4807.3374,"KHRV":156.12418,"KHRV_NOW":730.505,"KHRV_FUTURE":4463.3857},"comingSoon":false,"hidden":false}