{"name":"Acre NFT","id":4690,"img":"4690.png","rarityScore":53.67581,"rarityRank":1018,"attributes":[{"type":"background","value":"Snowy Weather","rarity":0.12561983,"rarityScore":7.9605265,"ignoredForRarity":false,"ignoredForDisplay":false},{"type":"base","value":"Grassland Soil Base","rarity":0.50475204,"rarityScore":1.9811707,"ignoredForRarity":false,"ignoredForDisplay":false},{"type":"life above","value":"Dragonfly","rarity":0.08698347,"rarityScore":11.496437,"ignoredForRarity":false,"ignoredForDisplay":false},{"type":"life below","value":"Texas Toad","rarity":0.1018595,"rarityScore":9.817444,"ignoredForRarity":false,"ignoredForDisplay":false},{"type":"tree","value":"Bur Oak","rarity":0.11095041,"rarityScore":9.013036,"ignoredForRarity":false,"ignoredForDisplay":false},{"type":"microorganism","value":"Amoeba","rarity":0.07458678,"rarityScore":13.407202,"ignoredForRarity":false,"ignoredForDisplay":false}],"prices":{"KRV":167.64143,"KARV_NOW":784.3942,"KARV_FUTURE":4792.649,"KHRV":156.11893,"KHRV_NOW":730.48047,"KHRV_FUTURE":4463.236},"comingSoon":false,"hidden":false}