{
 "name": "IBC Frens #3065",
 "id": 3065,
 "img": "3065.jpg",
 "rarityScore": 238.1016,
 "rarityRank": 2174,
 "attributes": [
  {
   "type": "Background",
   "value": "Space Blue",
   "rarity": 0.055,
   "rarityScore": 18.181818
  },
  {
   "type": "Character",
   "value": "Tattoo Light Green",
   "rarity": 0.0094,
   "rarityScore": 106.38298
  },
  {
   "type": "Body",
   "value": "Naked",
   "rarity": 0.1564,
   "rarityScore": 6.393862
  },
  {
   "type": "Eyes",
   "value": "Normal Light Green",
   "rarity": 0.0398,
   "rarityScore": 25.125628
  },
  {
   "type": "Mouth",
   "value": "Grumpy",
   "rarity": 0.0994,
   "rarityScore": 10.060362
  },
  {
   "type": "Head",
   "value": "Head Band Blue",
   "rarity": 0.0238,
   "rarityScore": 42.016808
  },
  {
   "type": "Antennas",
   "value": "Bolts Light Green",
   "rarity": 0.0334,
   "rarityScore": 29.94012
  },
  {
   "type": "generation",
   "value": "3065",
   "rarity": 0,
   "rarityScore": 0
  }
 ],
 "prices": {
  "KRV": 400.058,
  "KARV_NOW": 1871.8715,
  "KARV_FUTURE": 11437.135,
  "KHRV": 144.26274,
  "KHRV_NOW": 675.0054,
  "KHRV_FUTURE": 4124.2827
 }
}