{
 "name": "Stargaze Punks #3664",
 "id": 3664,
 "img": "3664.png",
 "rarityScore": 332.13806,
 "rarityRank": 2763,
 "attributes": [
  {
   "type": "Background",
   "value": "purple_hex_space",
   "rarity": 0.045342036,
   "rarityScore": 22.05459
  },
  {
   "type": "Glow",
   "value": "white_headglow",
   "rarity": 0.09225923,
   "rarityScore": 10.839025
  },
  {
   "type": "Back",
   "value": "pink_neonbackstaff",
   "rarity": 0.040841583,
   "rarityScore": 24.484848
  },
  {
   "type": "Species",
   "value": "humanoid7",
   "rarity": 0.122749776,
   "rarityScore": 8.146654
  },
  {
   "type": "FaceDetail",
   "value": "eyescar",
   "rarity": 0.060868587,
   "rarityScore": 16.428835
  },
  {
   "type": "Mouth",
   "value": "rassberry_mouth",
   "rarity": 0.11577408,
   "rarityScore": 8.637512
  },
  {
   "type": "Eyes",
   "value": "red_eyes",
   "rarity": 0.11971197,
   "rarityScore": 8.353383
  },
  {
   "type": "Tops",
   "value": "litegraycloak",
   "rarity": 0.017551756,
   "rarityScore": 56.974358
  },
  {
   "type": "Hair",
   "value": "purplebackwave_hair",
   "rarity": 0.013726372,
   "rarityScore": 72.85246
  },
  {
   "type": "Front",
   "value": "single_antenna",
   "rarity": 0.009788479,
   "rarityScore": 102.16092
  },
  {
   "type": "Bubble",
   "value": "empty",
   "rarity": 0.82954544,
   "rarityScore": 1.2054795
  }
 ],
 "prices": {
  "KRV": 381.57935,
  "KARV_NOW": 1785.4097,
  "KARV_FUTURE": 10908.854,
  "KHRV": 151.33716,
  "KHRV_NOW": 708.10657,
  "KHRV_FUTURE": 4326.5312
 }
}