{"name":"IBC Frens #1764","id":1764,"img":"1764.jpg","rarityScore":141.94444,"rarityRank":4216,"attributes":[{"type":"Background","value":"Rainbow Green","rarity":0.0364,"rarityScore":27.472527,"ignoredForRarity":false,"ignoredForDisplay":false},{"type":"Character","value":"Alien Light Pink","rarity":0.1228,"rarityScore":8.143323,"ignoredForRarity":false,"ignoredForDisplay":false},{"type":"Body","value":"Striped Shirt Pastel","rarity":0.0228,"rarityScore":43.85965,"ignoredForRarity":false,"ignoredForDisplay":false},{"type":"Eyes","value":"Grumpy","rarity":0.0622,"rarityScore":16.077171,"ignoredForRarity":false,"ignoredForDisplay":false},{"type":"Mouth","value":"Surprised","rarity":0.1112,"rarityScore":8.9928055,"ignoredForRarity":false,"ignoredForDisplay":false},{"type":"Head","value":"Head Band Yellow","rarity":0.0278,"rarityScore":35.971222,"ignoredForRarity":false,"ignoredForDisplay":false},{"type":"Antennas","value":"None","rarity":0.7004,"rarityScore":1.4277556,"ignoredForRarity":false,"ignoredForDisplay":false},{"type":"generation","value":"1764","rarity":0,"rarityScore":0,"ignoredForRarity":true,"ignoredForDisplay":true}],"prices":{"KRV":238.49489,"KARV_NOW":1115.9176,"KARV_FUTURE":6818.257,"KHRV":141.61449,"KHRV_NOW":662.6142,"KHRV_FUTURE":4048.5728},"comingSoon":false}