{
 "name": "IBC Frens #3826",
 "id": 3826,
 "img": "3826.jpg",
 "rarityScore": 235.17662,
 "rarityRank": 2240,
 "attributes": [
  {
   "type": "Background",
   "value": "Pastel 8",
   "rarity": 0.027,
   "rarityScore": 37.037037,
   "ignoredForRarity": false,
   "ignoredForDisplay": false
  },
  {
   "type": "Character",
   "value": "Alien Light Pink",
   "rarity": 0.1228,
   "rarityScore": 8.143323,
   "ignoredForRarity": false,
   "ignoredForDisplay": false
  },
  {
   "type": "Body",
   "value": "Shirt Light Yellow",
   "rarity": 0.0176,
   "rarityScore": 56.81818,
   "ignoredForRarity": false,
   "ignoredForDisplay": false
  },
  {
   "type": "Eyes",
   "value": "Hearts Yellow",
   "rarity": 0.0176,
   "rarityScore": 56.81818,
   "ignoredForRarity": false,
   "ignoredForDisplay": false
  },
  {
   "type": "Mouth",
   "value": "Satisfied",
   "rarity": 0.152,
   "rarityScore": 6.5789475,
   "ignoredForRarity": false,
   "ignoredForDisplay": false
  },
  {
   "type": "Head",
   "value": "Head Band Green",
   "rarity": 0.0268,
   "rarityScore": 37.313435,
   "ignoredForRarity": false,
   "ignoredForDisplay": false
  },
  {
   "type": "Antennas",
   "value": "Bolts Pink",
   "rarity": 0.0308,
   "rarityScore": 32.467533,
   "ignoredForRarity": false,
   "ignoredForDisplay": false
  },
  {
   "type": "generation",
   "value": "3826",
   "rarity": 0,
   "rarityScore": 0,
   "ignoredForRarity": true,
   "ignoredForDisplay": true
  }
 ],
 "prices": {
  "KRV": 395.1435,
  "KARV_NOW": 1848.8763,
  "KARV_FUTURE": 11296.635,
  "KHRV": 144.1822,
  "KHRV_NOW": 674.62854,
  "KHRV_FUTURE": 4121.9805
 }
}