{"name":"114Shut #1520","id":1520,"img":"1520.png","rarityScore":340.20688,"rarityRank":2216,"attributes":[{"type":"BASE COLOR","value":"Red","rarity":0.1414,"rarityScore":7.072136,"ignoredForRarity":false,"ignoredForDisplay":false},{"type":"BASE COLOR FX","value":"None","rarity":0.5534,"rarityScore":1.8070112,"ignoredForRarity":false,"ignoredForDisplay":false},{"type":"HARD CUT","value":"Curve TLM","rarity":0.0082,"rarityScore":121.95122,"ignoredForRarity":false,"ignoredForDisplay":false},{"type":"CIRCLE B\u0026W","value":"Circle TLBlk","rarity":0.0742,"rarityScore":13.477089,"ignoredForRarity":false,"ignoredForDisplay":false},{"type":"CIRCLE CLR","value":"None","rarity":0.416,"rarityScore":2.4038463,"ignoredForRarity":false,"ignoredForDisplay":false},{"type":"PATTERN","value":"17 of 25","rarity":0.0214,"rarityScore":46.728973,"ignoredForRarity":false,"ignoredForDisplay":false},{"type":"SHAPE","value":"Circle Right Eye C","rarity":0.022,"rarityScore":45.454544,"ignoredForRarity":false,"ignoredForDisplay":false},{"type":"MASK","value":"19 of 114","rarity":0.0102,"rarityScore":98.039215,"ignoredForRarity":false,"ignoredForDisplay":false},{"type":"HUE VARIATION","value":"None","rarity":0.557,"rarityScore":1.7953322,"ignoredForRarity":false,"ignoredForDisplay":false},{"type":"BACKGROUND","value":"None","rarity":0.6768,"rarityScore":1.4775413,"ignoredForRarity":false,"ignoredForDisplay":false}],"prices":{"KRV":403.50674,"KARV_NOW":1888.008,"KARV_FUTURE":11535.7295,"KHRV":119.46031,"KHRV_NOW":558.9548,"KHRV_FUTURE":3415.2136},"comingSoon":false,"hidden":false}