{"name":"114Shut #2014","id":2014,"img":"2014.png","rarityScore":299.726,"rarityRank":2992,"attributes":[{"type":"BASE COLOR","value":"Cyan","rarity":0.143,"rarityScore":6.993007,"ignoredForRarity":false,"ignoredForDisplay":false},{"type":"BASE COLOR FX","value":"None","rarity":0.5534,"rarityScore":1.8070112,"ignoredForRarity":false,"ignoredForDisplay":false},{"type":"HARD CUT","value":"Cut RWht","rarity":0.0182,"rarityScore":54.945053,"ignoredForRarity":false,"ignoredForDisplay":false},{"type":"CIRCLE B\u0026W","value":"None","rarity":0.365,"rarityScore":2.739726,"ignoredForRarity":false,"ignoredForDisplay":false},{"type":"CIRCLE CLR","value":"None","rarity":0.416,"rarityScore":2.4038463,"ignoredForRarity":false,"ignoredForDisplay":false},{"type":"PATTERN","value":"13 of 25","rarity":0.0212,"rarityScore":47.16981,"ignoredForRarity":false,"ignoredForDisplay":false},{"type":"SHAPE","value":"Circle Mouth M","rarity":0.0184,"rarityScore":54.347828,"ignoredForRarity":false,"ignoredForDisplay":false},{"type":"MASK","value":"6 of 114","rarity":0.0094,"rarityScore":106.38298,"ignoredForRarity":false,"ignoredForDisplay":false},{"type":"HUE VARIATION","value":"Soft R2","rarity":0.0466,"rarityScore":21.459227,"ignoredForRarity":false,"ignoredForDisplay":false},{"type":"BACKGROUND","value":"None","rarity":0.6768,"rarityScore":1.4775413,"ignoredForRarity":false,"ignoredForDisplay":false}],"prices":{"KRV":355.49393,"KARV_NOW":1663.3561,"KARV_FUTURE":10163.105,"KHRV":118.55475,"KHRV_NOW":554.71765,"KHRV_FUTURE":3389.325},"comingSoon":false}