{"name":"114Shut #2400","id":2400,"img":"2400.png","rarityScore":304.29056,"rarityRank":2915,"attributes":[{"type":"BASE COLOR","value":"Red","rarity":0.1414,"rarityScore":7.072136,"ignoredForRarity":false,"ignoredForDisplay":false},{"type":"BASE COLOR FX","value":"FX1","rarity":0.0254,"rarityScore":39.37008,"ignoredForRarity":false,"ignoredForDisplay":false},{"type":"HARD CUT","value":"Curve TRB","rarity":0.0114,"rarityScore":87.7193,"ignoredForRarity":false,"ignoredForDisplay":false},{"type":"CIRCLE B\u0026W","value":"Circle TLBlk","rarity":0.0742,"rarityScore":13.477089,"ignoredForRarity":false,"ignoredForDisplay":false},{"type":"CIRCLE CLR","value":"None","rarity":0.416,"rarityScore":2.4038463,"ignoredForRarity":false,"ignoredForDisplay":false},{"type":"PATTERN","value":"None","rarity":0.283,"rarityScore":3.5335689,"ignoredForRarity":false,"ignoredForDisplay":false},{"type":"SHAPE","value":"Star Wht","rarity":0.036,"rarityScore":27.777779,"ignoredForRarity":false,"ignoredForDisplay":false},{"type":"MASK","value":"111 of 114","rarity":0.01,"rarityScore":100,"ignoredForRarity":false,"ignoredForDisplay":false},{"type":"HUE VARIATION","value":"Soft R2","rarity":0.0466,"rarityScore":21.459227,"ignoredForRarity":false,"ignoredForDisplay":false},{"type":"BACKGROUND","value":"None","rarity":0.6768,"rarityScore":1.4775413,"ignoredForRarity":false,"ignoredForDisplay":false}],"prices":{"KRV":360.90775,"KARV_NOW":1688.6873,"KARV_FUTURE":10317.879,"KHRV":118.65685,"KHRV_NOW":555.1954,"KHRV_FUTURE":3392.244}}