{"name":"114Shut #4307","id":4307,"img":"4307.png","rarityScore":460.33197,"rarityRank":439,"attributes":[{"type":"BASE COLOR","value":"Blue","rarity":0.1436,"rarityScore":6.9637885,"ignoredForRarity":false,"ignoredForDisplay":false},{"type":"BASE COLOR FX","value":"None","rarity":0.5534,"rarityScore":1.8070112,"ignoredForRarity":false,"ignoredForDisplay":false},{"type":"HARD CUT","value":"Cut RY","rarity":0.0076,"rarityScore":131.57895,"ignoredForRarity":false,"ignoredForDisplay":false},{"type":"CIRCLE B\u0026W","value":"Circle TRBlk","rarity":0.0704,"rarityScore":14.204545,"ignoredForRarity":false,"ignoredForDisplay":false},{"type":"CIRCLE CLR","value":"Circle TLY","rarity":0.0138,"rarityScore":72.46377,"ignoredForRarity":false,"ignoredForDisplay":false},{"type":"PATTERN","value":"11 of 25","rarity":0.0248,"rarityScore":40.322582,"ignoredForRarity":false,"ignoredForDisplay":false},{"type":"SHAPE","value":"Circle M","rarity":0.0172,"rarityScore":58.139534,"ignoredForRarity":false,"ignoredForDisplay":false},{"type":"MASK","value":"74 of 114","rarity":0.0076,"rarityScore":131.57895,"ignoredForRarity":false,"ignoredForDisplay":false},{"type":"HUE VARIATION","value":"None","rarity":0.557,"rarityScore":1.7953322,"ignoredForRarity":false,"ignoredForDisplay":false},{"type":"BACKGROUND","value":"None","rarity":0.6768,"rarityScore":1.4775413,"ignoredForRarity":false,"ignoredForDisplay":false}],"prices":{"KRV":545.98267,"KARV_NOW":2554.6528,"KARV_FUTURE":15608.929,"KHRV":122.1475,"KHRV_NOW":571.52814,"KHRV_FUTURE":3492.037}}