{"name":"Sunnyside Reapers 4614","id":4614,"img":"4614.png","rarityScore":77.04724,"rarityRank":5528,"attributes":[{"type":"Background","value":"Stone ","rarity":0.06615662,"rarityScore":15.115646,"ignoredForRarity":false,"ignoredForDisplay":false},{"type":"Border","value":"U.S.A. ","rarity":0.090009004,"rarityScore":11.11,"ignoredForRarity":false,"ignoredForDisplay":false},{"type":"Scythe","value":"Trident ","rarity":0.049954996,"rarityScore":20.018019,"ignoredForRarity":false,"ignoredForDisplay":false},{"type":"Reaper","value":"Gold","rarity":0.105610564,"rarityScore":9.46875,"ignoredForRarity":false,"ignoredForDisplay":false},{"type":"Accessory","value":"None ","rarity":0.3760876,"rarityScore":2.6589549,"ignoredForRarity":false,"ignoredForDisplay":false},{"type":"Hand","value":"Sword ","rarity":0.06510651,"rarityScore":15.3594475,"ignoredForRarity":false,"ignoredForDisplay":false},{"type":"Head","value":"None ","rarity":0.30153015,"rarityScore":3.316418,"ignoredForRarity":false,"ignoredForDisplay":false}],"prices":{"KRV":137.20427,"KARV_NOW":641.97876,"KARV_FUTURE":3922.4902,"KHRV":66.3937,"KHRV_NOW":310.65613,"KHRV_FUTURE":1898.109}}