{"name":"Sunnyside Reapers 4966","id":4966,"img":"4966.png","rarityScore":0,"rarityRank":0,"attributes":[{"type":"Background","value":"Steel Blue ","rarity":0.080408044,"rarityScore":12.436567,"ignoredForRarity":false,"ignoredForDisplay":false},{"type":"Border","value":"Pride ","rarity":0.06615662,"rarityScore":15.115646,"ignoredForRarity":false,"ignoredForDisplay":false},{"type":"Scythe","value":"Mailbox ","rarity":0.04650465,"rarityScore":21.503225,"ignoredForRarity":false,"ignoredForDisplay":false},{"type":"Reaper","value":"Orange","rarity":0.10156015,"rarityScore":9.846381,"ignoredForRarity":false,"ignoredForDisplay":false},{"type":"Accessory","value":"Blue Eyed Dreamer ","rarity":0.027152715,"rarityScore":36.828728,"ignoredForRarity":false,"ignoredForDisplay":false},{"type":"Hand","value":"Light Sword (Blue) ","rarity":0.010951095,"rarityScore":91.31507,"ignoredForRarity":false,"ignoredForDisplay":false},{"type":"Head","value":"Ice Cold Beanie ","rarity":0.019951995,"rarityScore":50.1203,"ignoredForRarity":false,"ignoredForDisplay":false}],"prices":{"KRV":0,"KARV_NOW":0,"KARV_FUTURE":0,"KHRV":0,"KHRV_NOW":0,"KHRV_FUTURE":0},"comingSoon":true,"hidden":false}