{
 "name": "Stargaze Punks #1538",
 "id": 1538,
 "img": "1538.png",
 "rarityScore": 387.48343,
 "rarityRank": 1531,
 "attributes": [
  {
   "type": "Background",
   "value": "galactic_orb",
   "rarity": 0.01710171,
   "rarityScore": 58.473682
  },
  {
   "type": "Glow",
   "value": "pink_headglow",
   "rarity": 0.09619712,
   "rarityScore": 10.395322
  },
  {
   "type": "Back",
   "value": "purple_jetpack",
   "rarity": 0.038928892,
   "rarityScore": 25.68786
  },
  {
   "type": "Species",
   "value": "yakshian",
   "rarity": 0.03577858,
   "rarityScore": 27.949686
  },
  {
   "type": "FaceDetail",
   "value": "shinobi_band",
   "rarity": 0.013613861,
   "rarityScore": 73.454544
  },
  {
   "type": "Mouth",
   "value": "basic_mouth",
   "rarity": 0.3921017,
   "rarityScore": 2.5503588
  },
  {
   "type": "Eyes",
   "value": "magenta_eyes",
   "rarity": 0.12308731,
   "rarityScore": 8.124314
  },
  {
   "type": "Tops",
   "value": "classic_whiteshirt",
   "rarity": 0.03881638,
   "rarityScore": 25.76232
  },
  {
   "type": "Hair",
   "value": "redmidsideslick_hair",
   "rarity": 0.01080108,
   "rarityScore": 92.583336
  },
  {
   "type": "Front",
   "value": "black_skullmask",
   "rarity": 0.016314132,
   "rarityScore": 61.29655
  },
  {
   "type": "Bubble",
   "value": "empty",
   "rarity": 0.82954544,
   "rarityScore": 1.2054795
  }
 ],
 "prices": {
  "KRV": 445.16327,
  "KARV_NOW": 2082.919,
  "KARV_FUTURE": 12726.635,
  "KHRV": 152.24559,
  "KHRV_NOW": 712.3571,
  "KHRV_FUTURE": 4352.502
 }
}