{"name":"Stargaze Punks #1685","id":1685,"img":"1685.png","rarityScore":345.76294,"rarityRank":2393,"attributes":[{"type":"Background","value":"candy_sky_ship","rarity":0.05220522,"rarityScore":19.155172,"ignoredForRarity":false,"ignoredForDisplay":false},{"type":"Glow","value":"green_headglow","rarity":0.08809631,"rarityScore":11.351213,"ignoredForRarity":false,"ignoredForDisplay":false},{"type":"Back","value":"darkpurple_jetpack","rarity":0.042191718,"rarityScore":23.701334,"ignoredForRarity":false,"ignoredForDisplay":false},{"type":"Species","value":"humanoid2","rarity":0.12972547,"rarityScore":7.708586,"ignoredForRarity":false,"ignoredForDisplay":false},{"type":"FaceDetail","value":"shinobi_band","rarity":0.013613861,"rarityScore":73.454544,"ignoredForRarity":false,"ignoredForDisplay":false},{"type":"Mouth","value":"smaller_mouth","rarity":0.3797255,"rarityScore":2.6334815,"ignoredForRarity":false,"ignoredForDisplay":false},{"type":"Eyes","value":"basic_eyes","rarity":0.16876687,"rarityScore":5.9253335,"ignoredForRarity":false,"ignoredForDisplay":false},{"type":"Tops","value":"magentahoodie","rarity":0.01980198,"rarityScore":50.5,"ignoredForRarity":false,"ignoredForDisplay":false},{"type":"Hair","value":"blackbackslick_hair","rarity":0.021377137,"rarityScore":46.778946,"ignoredForRarity":false,"ignoredForDisplay":false},{"type":"Front","value":"redgreen_visor","rarity":0.0096759675,"rarityScore":103.34884,"ignoredForRarity":false,"ignoredForDisplay":false},{"type":"Bubble","value":"empty","rarity":0.82954544,"rarityScore":1.2054795,"ignoredForRarity":false,"ignoredForDisplay":false}],"prices":{"KRV":397.2324,"KARV_NOW":1858.6503,"KARV_FUTURE":11356.354,"KHRV":151.56079,"KHRV_NOW":709.15295,"KHRV_FUTURE":4332.925},"comingSoon":false,"hidden":false}