{"name":"Starchoadz #173","id":173,"img":"173.png","rarityScore":84.52386,"rarityRank":6784,"attributes":[{"type":"Background","value":"Solar Mass","rarity":0.06155833,"rarityScore":16.244755,"ignoredForRarity":false,"ignoredForDisplay":false},{"type":"Body","value":"Undead Female","rarity":0.021810876,"rarityScore":45.848682,"ignoredForRarity":false,"ignoredForDisplay":false},{"type":"Head","value":"None","rarity":0.56636536,"rarityScore":1.7656448,"ignoredForRarity":false,"ignoredForDisplay":false},{"type":"Mouth","value":"None","rarity":0.53092265,"rarityScore":1.8835136,"ignoredForRarity":false,"ignoredForDisplay":false},{"type":"Eyes","value":"None","rarity":0.40421867,"rarityScore":2.4739084,"ignoredForRarity":false,"ignoredForDisplay":false},{"type":"Clothes","value":"None","rarity":0.9800545,"rarityScore":1.0203514,"ignoredForRarity":false,"ignoredForDisplay":false},{"type":"Accessory 1","value":"None","rarity":0.8276654,"rarityScore":1.2082177,"ignoredForRarity":false,"ignoredForDisplay":false},{"type":"Accessory 2","value":"Earring","rarity":0.07102884,"rarityScore":14.078788,"ignoredForRarity":false,"ignoredForDisplay":false}],"prices":{"KRV":119.5234,"KARV_NOW":559.25,"KARV_FUTURE":3417.0176,"KHRV":69.351295,"KHRV_NOW":324.4947,"KHRV_FUTURE":1982.6626},"comingSoon":false,"hidden":false}