{"name":"Starchoadz #3531","id":3531,"img":"3531.png","rarityScore":224.97734,"rarityRank":2926,"attributes":[{"type":"Background","value":"Spiral Galaxy","rarity":0.074903145,"rarityScore":13.3505745,"ignoredForRarity":false,"ignoredForDisplay":false},{"type":"Body","value":"Undead Female","rarity":0.021810876,"rarityScore":45.848682,"ignoredForRarity":false,"ignoredForDisplay":false},{"type":"Head","value":"Aqua Sidepart","rarity":0.008896542,"rarityScore":112.40323,"ignoredForRarity":false,"ignoredForDisplay":false},{"type":"Mouth","value":"Green Bucktooth","rarity":0.028698523,"rarityScore":34.845,"ignoredForRarity":false,"ignoredForDisplay":false},{"type":"Eyes","value":"None","rarity":0.40421867,"rarityScore":2.4739084,"ignoredForRarity":false,"ignoredForDisplay":false},{"type":"Clothes","value":"None","rarity":0.9800545,"rarityScore":1.0203514,"ignoredForRarity":false,"ignoredForDisplay":false},{"type":"Accessory 1","value":"None","rarity":0.8276654,"rarityScore":1.2082177,"ignoredForRarity":false,"ignoredForDisplay":false},{"type":"Accessory 2","value":"Watch","rarity":0.072320275,"rarityScore":13.827381,"ignoredForRarity":false,"ignoredForDisplay":false}],"prices":{"KRV":318.13568,"KARV_NOW":1488.5568,"KARV_FUTURE":9095.082,"KHRV":70.732254,"KHRV_NOW":330.9562,"KHRV_FUTURE":2022.1425},"comingSoon":false,"hidden":false}