{"name":"Starchoadz #4064","id":4064,"img":"4064.png","rarityScore":317.55334,"rarityRank":1203,"attributes":[{"type":"Background","value":"Spiral Galaxy","rarity":0.074903145,"rarityScore":13.3505745,"ignoredForRarity":false,"ignoredForDisplay":false},{"type":"Body","value":"Gummy Raspberry Female","rarity":0.011909886,"rarityScore":83.96385,"ignoredForRarity":false,"ignoredForDisplay":false},{"type":"Head","value":"Swampy Sidepart","rarity":0.0055962116,"rarityScore":178.6923,"ignoredForRarity":false,"ignoredForDisplay":false},{"type":"Mouth","value":"Green Bucktooth","rarity":0.028698523,"rarityScore":34.845,"ignoredForRarity":false,"ignoredForDisplay":false},{"type":"Eyes","value":"None","rarity":0.40421867,"rarityScore":2.4739084,"ignoredForRarity":false,"ignoredForDisplay":false},{"type":"Clothes","value":"None","rarity":0.9800545,"rarityScore":1.0203514,"ignoredForRarity":false,"ignoredForDisplay":false},{"type":"Accessory 1","value":"None","rarity":0.8276654,"rarityScore":1.2082177,"ignoredForRarity":false,"ignoredForDisplay":false},{"type":"Accessory 2","value":"None","rarity":0.50021523,"rarityScore":1.9991394,"ignoredForRarity":false,"ignoredForDisplay":false}],"prices":{"KRV":449.04544,"KARV_NOW":2101.0835,"KARV_FUTURE":12837.62,"KHRV":71.64247,"KHRV_NOW":335.21512,"KHRV_FUTURE":2048.1643},"comingSoon":false,"hidden":false}