{"name":"Starchoadz #5212","id":5212,"img":"5212.png","rarityScore":179.69727,"rarityRank":4147,"attributes":[{"type":"Background","value":"Redshift","rarity":0.0698809,"rarityScore":14.310061,"ignoredForRarity":false,"ignoredForDisplay":false},{"type":"Body","value":"Gremplin Blue Male","rarity":0.014923232,"rarityScore":67.00961,"ignoredForRarity":false,"ignoredForDisplay":false},{"type":"Head","value":"None","rarity":0.56636536,"rarityScore":1.7656448,"ignoredForRarity":false,"ignoredForDisplay":false},{"type":"Mouth","value":"Sad","rarity":0.035873152,"rarityScore":27.876,"ignoredForRarity":false,"ignoredForDisplay":false},{"type":"Eyes","value":"Dilated","rarity":0.027263597,"rarityScore":36.678947,"ignoredForRarity":false,"ignoredForDisplay":false},{"type":"Clothes","value":"None","rarity":0.9800545,"rarityScore":1.0203514,"ignoredForRarity":false,"ignoredForDisplay":false},{"type":"Accessory 1","value":"Four Flies","rarity":0.034438226,"rarityScore":29.0375,"ignoredForRarity":false,"ignoredForDisplay":false},{"type":"Accessory 2","value":"None","rarity":0.50021523,"rarityScore":1.9991394,"ignoredForRarity":false,"ignoredForDisplay":false}],"prices":{"KRV":254.1061,"KARV_NOW":1188.9624,"KARV_FUTURE":7264.5605,"KHRV":70.28705,"KHRV_NOW":328.87308,"KHRV_FUTURE":2009.4146},"comingSoon":false,"hidden":false}