{"name":"Starchoadz #6629","id":6629,"img":"6629.png","rarityScore":126.80096,"rarityRank":5818,"attributes":[{"type":"Background","value":"Redshift","rarity":0.0698809,"rarityScore":14.310061,"ignoredForRarity":false,"ignoredForDisplay":false},{"type":"Body","value":"Albino Male","rarity":0.018510547,"rarityScore":54.023254,"ignoredForRarity":false,"ignoredForDisplay":false},{"type":"Head","value":"None","rarity":0.56636536,"rarityScore":1.7656448,"ignoredForRarity":false,"ignoredForDisplay":false},{"type":"Mouth","value":"None","rarity":0.53092265,"rarityScore":1.8835136,"ignoredForRarity":false,"ignoredForDisplay":false},{"type":"Eyes","value":"Dilated","rarity":0.027263597,"rarityScore":36.678947,"ignoredForRarity":false,"ignoredForDisplay":false},{"type":"Clothes","value":"None","rarity":0.9800545,"rarityScore":1.0203514,"ignoredForRarity":false,"ignoredForDisplay":false},{"type":"Accessory 1","value":"None","rarity":0.8276654,"rarityScore":1.2082177,"ignoredForRarity":false,"ignoredForDisplay":false},{"type":"Accessory 2","value":"Shackles","rarity":0.06284976,"rarityScore":15.910959,"ignoredForRarity":false,"ignoredForDisplay":false}],"prices":{"KRV":179.30655,"KARV_NOW":838.97534,"KARV_FUTURE":5126.1396,"KHRV":69.76697,"KHRV_NOW":326.43964,"KHRV_FUTURE":1994.5463},"comingSoon":false,"hidden":false}