{"name":"Wad #1518","id":1518,"img":"1517.png","rarityScore":283.1991,"rarityRank":2697,"attributes":[{"type":"Background","value":"Brown","rarity":0.027555555,"rarityScore":36.29032,"ignoredForRarity":false,"ignoredForDisplay":false},{"type":"Body","value":"CreepWad","rarity":0.010111111,"rarityScore":98.9011,"ignoredForRarity":false,"ignoredForDisplay":false},{"type":"Eyes","value":"Green Eyeshadow","rarity":0.011444445,"rarityScore":87.37864,"ignoredForRarity":false,"ignoredForDisplay":false},{"type":"Mouth","value":"Peach Smile","rarity":0.071444444,"rarityScore":13.996889,"ignoredForRarity":false,"ignoredForDisplay":false},{"type":"Head","value":"Aqua Sidepart","rarity":0.021444444,"rarityScore":46.632126,"ignoredForRarity":false,"ignoredForDisplay":false}],"prices":{"KRV":853.41394,"KARV_NOW":3993.1238,"KARV_FUTURE":24397.986,"KHRV":102.76773,"KHRV_NOW":480.8502,"KHRV_FUTURE":2937.9946}}