{"name":"Wad #2847","id":2847,"img":"2846.png","rarityScore":267.03238,"rarityRank":3057,"attributes":[{"type":"Background","value":"Greenieeee","rarity":0.027555555,"rarityScore":36.29032,"ignoredForRarity":false,"ignoredForDisplay":false},{"type":"Special","value":"1 Fly","rarity":0.029444445,"rarityScore":33.962265,"ignoredForRarity":false,"ignoredForDisplay":false},{"type":"Body","value":"Blue CatWad","rarity":0.017111111,"rarityScore":58.44156,"ignoredForRarity":false,"ignoredForDisplay":false},{"type":"Eyes","value":"Red And White Goggles","rarity":0.048444446,"rarityScore":20.642202,"ignoredForRarity":false,"ignoredForDisplay":false},{"type":"Mouth","value":"Green Bucktooth","rarity":0.043555554,"rarityScore":22.959183,"ignoredForRarity":false,"ignoredForDisplay":false},{"type":"Head","value":"Mage","rarity":0.010555555,"rarityScore":94.73684,"ignoredForRarity":false,"ignoredForDisplay":false}],"prices":{"KRV":804.696,"KARV_NOW":3765.1724,"KARV_FUTURE":23005.203,"KHRV":102.58876,"KHRV_NOW":480.0128,"KHRV_FUTURE":2932.8782}}