{"name":"Wad #3186","id":3186,"img":"3185.png","rarityScore":177.96219,"rarityRank":5872,"attributes":[{"type":"Background","value":"Dreige","rarity":0.068555556,"rarityScore":14.58671,"ignoredForRarity":false,"ignoredForDisplay":false},{"type":"Body","value":"Orange CatWad","rarity":0.028666666,"rarityScore":34.88372,"ignoredForRarity":false,"ignoredForDisplay":false},{"type":"Eyes","value":"ThickRound","rarity":0.049666665,"rarityScore":20.134228,"ignoredForRarity":false,"ignoredForDisplay":false},{"type":"Mouth","value":"Yellow Smile","rarity":0.030555556,"rarityScore":32.727272,"ignoredForRarity":false,"ignoredForDisplay":false},{"type":"Head","value":"Short Feathered Hat","rarity":0.013222222,"rarityScore":75.63025,"ignoredForRarity":false,"ignoredForDisplay":false}],"prices":{"KRV":536.285,"KARV_NOW":2509.2773,"KARV_FUTURE":15331.685,"KHRV":101.60273,"KHRV_NOW":475.39917,"KHRV_FUTURE":2904.689}}