{"name":"Wad #5273","id":5273,"img":"5272.png","rarityScore":0,"rarityRank":0,"attributes":[{"type":"Background","value":"Grey Foam","rarity":0.011555555,"rarityScore":86.53846,"ignoredForRarity":false,"ignoredForDisplay":false},{"type":"Body","value":"FireWad","rarity":0.047111113,"rarityScore":21.226416,"ignoredForRarity":false,"ignoredForDisplay":false},{"type":"Eyes","value":"ThickRound","rarity":0.049666665,"rarityScore":20.134228,"ignoredForRarity":false,"ignoredForDisplay":false},{"type":"Head","value":"Backwards Cap","rarity":0.03522222,"rarityScore":28.391167,"ignoredForRarity":false,"ignoredForDisplay":false}],"prices":{"KRV":0,"KARV_NOW":0,"KARV_FUTURE":0,"KHRV":0,"KHRV_NOW":0,"KHRV_FUTURE":0},"comingSoon":true,"hidden":false}