{"name":"Wad #5508","id":5508,"img":"5507.png","rarityScore":105.3955,"rarityRank":8480,"attributes":[{"type":"Background","value":"Dreige","rarity":0.068555556,"rarityScore":14.58671,"ignoredForRarity":false,"ignoredForDisplay":false},{"type":"Body","value":"ChimpWad","rarity":0.043,"rarityScore":23.255814,"ignoredForRarity":false,"ignoredForDisplay":false},{"type":"Eyes","value":"Black And Red Goggles","rarity":0.04622222,"rarityScore":21.634615,"ignoredForRarity":false,"ignoredForDisplay":false},{"type":"Head","value":"Shhh","rarity":0.021777777,"rarityScore":45.918365,"ignoredForRarity":false,"ignoredForDisplay":false}],"prices":{"KRV":317.60693,"KARV_NOW":1486.0828,"KARV_FUTURE":9079.966,"KHRV":100.79939,"KHRV_NOW":471.64035,"KHRV_FUTURE":2881.7227}}