{"name":"Wad #5513","id":5513,"img":"5512.png","rarityScore":274.22592,"rarityRank":2892,"attributes":[{"type":"Background","value":"Hot Pink","rarity":0.020555556,"rarityScore":48.648647,"ignoredForRarity":false,"ignoredForDisplay":false},{"type":"Body","value":"BerryWad","rarity":0.03511111,"rarityScore":28.481012,"ignoredForRarity":false,"ignoredForDisplay":false},{"type":"Eyes","value":"ThickRound","rarity":0.049666665,"rarityScore":20.134228,"ignoredForRarity":false,"ignoredForDisplay":false},{"type":"Head","value":"Swampy DoubleBun","rarity":0.008333334,"rarityScore":120,"ignoredForRarity":false,"ignoredForDisplay":false},{"type":"Accessory","value":"Cute Bow","rarity":0.017555555,"rarityScore":56.962025,"ignoredForRarity":false,"ignoredForDisplay":false}],"prices":{"KRV":826.3736,"KARV_NOW":3866.602,"KARV_FUTURE":23624.94,"KHRV":102.668396,"KHRV_NOW":480.3854,"KHRV_FUTURE":2935.1548}}