{"name":"Wad #8055","id":8055,"img":"8054.png","rarityScore":106.32689,"rarityRank":8460,"attributes":[{"type":"Background","value":"Yellow","rarity":0.058222223,"rarityScore":17.175573,"ignoredForRarity":false,"ignoredForDisplay":false},{"type":"Body","value":"MeatWad","rarity":0.093,"rarityScore":10.752688,"ignoredForRarity":false,"ignoredForDisplay":false},{"type":"Eyes","value":"Nounish Blue","rarity":0.067555554,"rarityScore":14.802631,"ignoredForRarity":false,"ignoredForDisplay":false},{"type":"Mouth","value":"Murk","rarity":0.03533333,"rarityScore":28.301888,"ignoredForRarity":false,"ignoredForDisplay":false},{"type":"Head","value":"Black Sidepart","rarity":0.028333334,"rarityScore":35.294117,"ignoredForRarity":false,"ignoredForDisplay":false}],"prices":{"KRV":320.41364,"KARV_NOW":1499.2153,"KARV_FUTURE":9160.206,"KHRV":100.80971,"KHRV_NOW":471.6886,"KHRV_FUTURE":2882.0173}}