{"name":"Wad #8534","id":8534,"img":"8533.png","rarityScore":524.06635,"rarityRank":580,"attributes":[{"type":"Background","value":"Cream Purple","rarity":0.06711111,"rarityScore":14.900662,"ignoredForRarity":false,"ignoredForDisplay":false},{"type":"Body","value":"WadBot","rarity":0.006,"rarityScore":166.66667,"ignoredForRarity":false,"ignoredForDisplay":false},{"type":"Eyes","value":"Violet Goggles","rarity":0.060555555,"rarityScore":16.513762,"ignoredForRarity":false,"ignoredForDisplay":false},{"type":"Mouth","value":"Blood Smile","rarity":0.024777777,"rarityScore":40.358746,"ignoredForRarity":false,"ignoredForDisplay":false},{"type":"Head","value":"Orange TallHat","rarity":0.004888889,"rarityScore":204.54546,"ignoredForRarity":false,"ignoredForDisplay":false},{"type":"Accessory","value":"Cig","rarity":0.0123333335,"rarityScore":81.08108,"ignoredForRarity":false,"ignoredForDisplay":false}],"prices":{"KRV":1579.262,"KARV_NOW":7389.3667,"KARV_FUTURE":45149.03,"KHRV":105.434204,"KHRV_NOW":493.32663,"KHRV_FUTURE":3014.2258}}