{"name":"Wad #8957","id":8957,"img":"8956.png","rarityScore":628.00775,"rarityRank":331,"attributes":[{"type":"Background","value":"Blanket","rarity":0.085666664,"rarityScore":11.673152,"ignoredForRarity":false,"ignoredForDisplay":false},{"type":"Body","value":"HypnoticWad","rarity":0.005,"rarityScore":200,"ignoredForRarity":false,"ignoredForDisplay":false},{"type":"Eyes","value":"ThugLyfeee","rarity":0.004,"rarityScore":250,"ignoredForRarity":false,"ignoredForDisplay":false},{"type":"Mouth","value":"Beard","rarity":0.05,"rarityScore":20,"ignoredForRarity":false,"ignoredForDisplay":false},{"type":"Head","value":"Blue Pigtails","rarity":0.008888889,"rarityScore":112.5,"ignoredForRarity":false,"ignoredForDisplay":false},{"type":"Accessory","value":"Button","rarity":0.029555555,"rarityScore":33.834587,"ignoredForRarity":false,"ignoredForDisplay":false}],"prices":{"KRV":1892.4869,"KARV_NOW":8854.946,"KARV_FUTURE":54103.723,"KHRV":106.58487,"KHRV_NOW":498.7106,"KHRV_FUTURE":3047.1218}}